orbis_plugin_storage_export_results/__init__.py
orbis_plugin_storage_export_results/main.py
orbis_plugin_storage_export_results-1.1.dev2.dist-info/LICENSE
orbis_plugin_storage_export_results-1.1.dev2.dist-info/METADATA
orbis_plugin_storage_export_results-1.1.dev2.dist-info/WHEEL
orbis_plugin_storage_export_results-1.1.dev2.dist-info/top_level.txt
orbis_plugin_storage_export_results-1.1.dev2.dist-info/RECORD
